[
  {
    "title": "Кто стоял у основ технологии коммутации пакетов",
    "answers": [
      {
        "value": "Александр Грэхем Белл и Томас Алва Эдисон",
        "correct": "false"
      },
      {
        "value": "Пол Бэрен и Леонард Клейнрок",
        "correct": "true"
      },
      {
        "value": "Стив Джобс и (независимо) Билл Гейтс",
        "correct": "false"
      },
      {
        "value": "Ларри Робертс и Боб Тейлор",
        "correct": "false"
      }
    ]
  },
  {
    "title": "Данные в компьютерной сети передаются",
    "answers": [
      {
        "value": "Чемоданами",
        "correct": "false"
      },
      {
        "value": "Сумками",
        "correct": "false"
      },
      {
        "value": "Пакетами",
        "correct": "true"
      },
      {
        "value": "Ящиками",
        "correct": "false"
      }
    ]
  },
  {
    "title": "Какой вид коммутации гарантирует пропускную способность (полосу пропускания) для взаимодействующих абонентов",
    "answers": [
      {
        "value": "Канальная коммутация",
        "correct": "true"
      },
      {
        "value": "Пакетная коммутация",
        "correct": "false"
      },
      {
        "value": "Туннельная коммутация",
        "correct": "false"
      },
      {
        "value": "Перекрестная коммутация",
        "correct": "false"
      }
    ]
  },
  {
    "title": "При каком виде коммутации данные состоят из двух частей: заголовок и данные",
    "answers": [
      {
        "value": "Пакетная",
        "correct": "true"
      },
      {
        "value": "Канальная",
        "correct": "false"
      },
      {
        "value": "Телефонная",
        "correct": "false"
      },
      {
        "value": "Компьютерная",
        "correct": "false"
      }
    ]
  },
  {
    "title": "Коммутация пакетов это",
    "answers": [
      {
        "value": "Передача данных с помощью современных цифровых сетей",
        "correct": "false"
      },
      {
        "value": "Использование пакетного коммутатора для передачи сообщений",
        "correct": "false"
      },
      {
        "value": "Передача сообщения в виде нескольких частей, называемых пакетами",
        "correct": "true"
      },
      {
        "value": "Использование маршрутизатора для передачи сообщений",
        "correct": "false"
      }
    ]
  }
]
